Metadata-Version: 2.1
Name: utensils
Version: 0.0.43
Summary: Library of utilities for python
Home-page: UNKNOWN
License: BSD
Platform: UNKNOWN
Classifier: License :: OSI Approved :: BSD License
